odoo/addons/stock_picking_product_barcode_report/README.rst
odoo/addons/stock_picking_product_barcode_report/__init__.py
odoo/addons/stock_picking_product_barcode_report/__manifest__.py
odoo/addons/stock_picking_product_barcode_report/controllers/__init__.py
odoo/addons/stock_picking_product_barcode_report/controllers/main.py
odoo/addons/stock_picking_product_barcode_report/data/ir_actions_report_data.xml
odoo/addons/stock_picking_product_barcode_report/data/paperformat_label.xml
odoo/addons/stock_picking_product_barcode_report/i18n/es.po
odoo/addons/stock_picking_product_barcode_report/i18n/stock_picking_product_barcode_report.pot
odoo/addons/stock_picking_product_barcode_report/models/__init__.py
odoo/addons/stock_picking_product_barcode_report/models/ir_actions_report.py
odoo/addons/stock_picking_product_barcode_report/models/res_company.py
odoo/addons/stock_picking_product_barcode_report/models/res_config_settings.py
odoo/addons/stock_picking_product_barcode_report/readme/CONFIGURE.rst
odoo/addons/stock_picking_product_barcode_report/readme/CONTRIBUTORS.rst
odoo/addons/stock_picking_product_barcode_report/readme/DESCRIPTION.rst
odoo/addons/stock_picking_product_barcode_report/readme/USAGE.rst
odoo/addons/stock_picking_product_barcode_report/report/report_label_barcode.xml
odoo/addons/stock_picking_product_barcode_report/report/report_label_barcode_quant_package_template.xml
odoo/addons/stock_picking_product_barcode_report/report/report_label_barcode_template.xml
odoo/addons/stock_picking_product_barcode_report/static/description/icon.png
odoo/addons/stock_picking_product_barcode_report/static/description/index.html
odoo/addons/stock_picking_product_barcode_report/tests/__init__.py
odoo/addons/stock_picking_product_barcode_report/tests/test_stock_picking_product_barcode_report.py
odoo/addons/stock_picking_product_barcode_report/views/ir_actions_report_view.xml
odoo/addons/stock_picking_product_barcode_report/views/res_config_settings_view.xml
odoo13_addon_stock_picking_product_barcode_report-13.0.2.2.0.dist-info/METADATA
odoo13_addon_stock_picking_product_barcode_report-13.0.2.2.0.dist-info/WHEEL
odoo13_addon_stock_picking_product_barcode_report-13.0.2.2.0.dist-info/top_level.txt
odoo13_addon_stock_picking_product_barcode_report-13.0.2.2.0.dist-info/RECORD
