Metadata-Version: 2.1
Name: odoo13-addon-stock-picking-product-barcode-report
Version: 13.0.2.2.0
Summary: It provides a wizard to select how many barcodes print.
Home-page: https://odoo-community.org/
Author: Tecnativa, Odoo Community Association (OCA)
Author-email: support@odoo-community.org
License: AGPL-3
Platform: UNKNOWN
Classifier: Programming Language :: Python
Classifier: Framework :: Odoo
Classifier: Framework :: Odoo :: 13.0
Classifier: License :: OSI Approved :: GNU Affero General Public License v3
Requires-Python: >=3.5
Requires-Dist: odoo (<13.1dev,>=13.0a)
Requires-Dist: python-barcode
